
{
    "$jason": {
        "head": {
            "title": "{ ˃̵̑ᴥ˂̵̑}"
        },
        "body": {
            "style": {
                "background": "#ffffff",
                "border": "none"
            },
            "sections": [
                {
                    "items": [
                        {
                            "type": "vertical",
                            "style": {
                                "padding": 30,
                                "spacing": 20,
                                "align": "center"
                            },
                            "components": [
                                {
                                    "type": "label",
                                    "text": "Welcome to ZeFi",
                                    "style": {
                                        "align": "center",
                                        "font": "Courier-Bold",
                                        "size": 26
                                    }
                                }
                            ]
                        }
                    ]
                }
            ]
        }
    }
}
